ai_odoofinder_mcp/__init__.py
ai_odoofinder_mcp/server.py
ai_odoofinder_mcp-1.0.0.dist-info/METADATA
ai_odoofinder_mcp-1.0.0.dist-info/WHEEL
ai_odoofinder_mcp-1.0.0.dist-info/entry_points.txt
ai_odoofinder_mcp-1.0.0.dist-info/RECORD
