Metadata-Version: 2.4
Name: ai-odoofinder-mcp
Version: 1.0.0
Summary: MCP Server for AI-OdooFinder - Semantic search for Odoo modules in the OCA ecosystem
Project-URL: Homepage, https://github.com/SantipBarber/ai-odoo-finder
Project-URL: Repository, https://github.com/SantipBarber/ai-odoo-finder
Project-URL: Documentation, https://github.com/SantipBarber/ai-odoo-finder/tree/main/mcp-server
Project-URL: Issues, https://github.com/SantipBarber/ai-odoo-finder/issues
Author-email: Santiago Pérez Barber <santipbr@gmail.com>
License-Expression: MIT
Keywords: ai,claude,llm,mcp,oca,odoo,search,semantic-search
Classifier: Development Status :: 4 - Beta
Classifier: Intended Audience :: Developers
Classifier: License :: OSI Approved :: MIT License
Classifier: Operating System :: OS Independent
Classifier: Programming Language :: Python :: 3
Classifier: Programming Language :: Python :: 3.11
Classifier: Programming Language :: Python :: 3.12
Classifier: Topic :: Scientific/Engineering :: Artificial Intelligence
Classifier: Topic :: Software Development :: Libraries :: Python Modules
Requires-Python: >=3.11
Requires-Dist: fastmcp>=2.0.0
Requires-Dist: httpx>=0.27.0
Requires-Dist: python-dotenv>=1.0.0
